pysdl/__init__.py
pysdl/logger_config.py
pysdl/stackdriverjsonlogger.py
pysdl-1.1.2.dist-info/METADATA
pysdl-1.1.2.dist-info/WHEEL
pysdl-1.1.2.dist-info/licenses/LICENSE
pysdl-1.1.2.dist-info/RECORD
