Metadata-Version: 2.1
Name: pysdl
Version: 1.1.2
Summary: A python library that helps Stackdriver consume python logs appropriately built on madzak/python-json-logger
Project-URL: Homepage, https://github.com/newtonx-inc/pysdl
Project-URL: Bug Tracker, https://github.com/newtonx-inc/pysdl/issues
Author-email: NewtonX <kristoph.matthews@newtonx.com>
License-File: LICENSE
Classifier: License :: OSI Approved :: MIT License
Classifier: Operating System :: OS Independent
Classifier: Programming Language :: Python :: 3
Requires-Python: >=3.4
Requires-Dist: python-json-logger==2.0.7
